pyfx/__init__.py
pyfx/pyfx.py
pyfx_tool-0.1.0.dist-info/COPYING
pyfx_tool-0.1.0.dist-info/LICENSE
pyfx_tool-0.1.0.dist-info/METADATA
pyfx_tool-0.1.0.dist-info/WHEEL
pyfx_tool-0.1.0.dist-info/entry_points.txt
pyfx_tool-0.1.0.dist-info/top_level.txt
pyfx_tool-0.1.0.dist-info/RECORD
