Metadata-Version: 2.1
Name: pyfx-tool
Version: 0.1.0
Summary: Fx (Function eXecution) in Python, inspired by https://www.npmjs.com/package/fx.
Home-page: https://github.com/archeraldrich/pyfx
Author: Wu Runfan
Author-email: Wu Runfan <alr_public@hotmail.com>
Project-URL: Homepage, https://github.com/archeraldrich/pyfx
Project-URL: Bug Tracker, https://github.com/archeraldrich/pyfx/issues
Classifier: Programming Language :: Python :: 3
Classifier: License :: OSI Approved :: MIT License
Classifier: Operating System :: OS Independent
Requires-Python: >=3.2
License-File: LICENSE
License-File: COPYING
Requires-Dist: json-stream-parser (>=0.0.1)
